{"frames": {

"big_back.png":
{
	"frame": {"x":2,"y":2,"w":2000,"h":2000},
	"rotated": false,
	"trimmed": false,
	"spriteSourceSize": {"x":0,"y":0,"w":2000,"h":2000},
	"sourceSize": {"w":2000,"h":2000},
	"pivot": {"x":0.5,"y":0.5}
},
"big_back2.png":
{
	"frame": {"x":2004,"y":2,"w":2000,"h":2000},
	"rotated": false,
	"trimmed": false,
	"spriteSourceSize": {"x":0,"y":0,"w":2000,"h":2000},
	"sourceSize": {"w":2000,"h":2000},
	"pivot": {"x":0.5,"y":0.5}
},
"brom1.png":
{
	"frame": {"x":1386,"y":2004,"w":97,"h":94},
	"rotated": false,
	"trimmed": false,
	"spriteSourceSize": {"x":0,"y":0,"w":97,"h":94},
	"sourceSize": {"w":97,"h":94},
	"pivot": {"x":0.5,"y":0.5}
},
"brom2.png":
{
	"frame": {"x":1565,"y":2004,"w":76,"h":96},
	"rotated": false,
	"trimmed": false,
	"spriteSourceSize": {"x":0,"y":0,"w":76,"h":96},
	"sourceSize": {"w":76,"h":96},
	"pivot": {"x":0.5,"y":0.5}
},
"brom3.png":
{
	"frame": {"x":1485,"y":2004,"w":78,"h":90},
	"rotated": false,
	"trimmed": false,
	"spriteSourceSize": {"x":0,"y":0,"w":78,"h":90},
	"sourceSize": {"w":78,"h":90},
	"pivot": {"x":0.5,"y":0.5}
},
"clawbot.png":
{
	"frame": {"x":1205,"y":2004,"w":179,"h":177},
	"rotated": false,
	"trimmed": false,
	"spriteSourceSize": {"x":0,"y":0,"w":179,"h":177},
	"sourceSize": {"w":179,"h":177},
	"pivot": {"x":0.5,"y":0.5}
},
"grom1.png":
{
	"frame": {"x":810,"y":2004,"w":200,"h":200},
	"rotated": false,
	"trimmed": false,
	"spriteSourceSize": {"x":0,"y":0,"w":200,"h":200},
	"sourceSize": {"w":200,"h":200},
	"pivot": {"x":0.5,"y":0.5}
},
"grom2.png":
{
	"frame": {"x":608,"y":2004,"w":200,"h":200},
	"rotated": false,
	"trimmed": false,
	"spriteSourceSize": {"x":0,"y":0,"w":200,"h":200},
	"sourceSize": {"w":200,"h":200},
	"pivot": {"x":0.5,"y":0.5}
},
"grom3.png":
{
	"frame": {"x":2,"y":2004,"w":200,"h":200},
	"rotated": false,
	"trimmed": false,
	"spriteSourceSize": {"x":0,"y":0,"w":200,"h":200},
	"sourceSize": {"w":200,"h":200},
	"pivot": {"x":0.5,"y":0.5}
},
"grom4.png":
{
	"frame": {"x":204,"y":2004,"w":200,"h":200},
	"rotated": false,
	"trimmed": false,
	"spriteSourceSize": {"x":0,"y":0,"w":200,"h":200},
	"sourceSize": {"w":200,"h":200},
	"pivot": {"x":0.5,"y":0.5}
},
"grom5.png":
{
	"frame": {"x":406,"y":2004,"w":200,"h":200},
	"rotated": false,
	"trimmed": false,
	"spriteSourceSize": {"x":0,"y":0,"w":200,"h":200},
	"sourceSize": {"w":200,"h":200},
	"pivot": {"x":0.5,"y":0.5}
},
"seeker.png":
{
	"frame": {"x":1012,"y":2004,"w":191,"h":186},
	"rotated": false,
	"trimmed": false,
	"spriteSourceSize": {"x":0,"y":0,"w":191,"h":186},
	"sourceSize": {"w":191,"h":186},
	"pivot": {"x":0.5,"y":0.5}
}},
"meta": {
	"app": "http://www.codeandweb.com/texturepacker",
	"version": "1.0",
	"image": "spritesheet.png",
	"format": "RGBA8888",
	"size": {"w":4006,"h":2206},
	"scale": "1",
	"smartupdate": "$TexturePacker:SmartUpdate:d43390d7bb624fda2c3fa06da7b10729:abf191e092053f70db533c14fbdb233b:729adc6043343cfda41c447ce8f464d6$"
}
}
